hugsvision/__init__.py
hugsvision/version.txt
hugsvision/dataio/CocoDetectionDataset.py
hugsvision/dataio/ImageClassificationCollator.py
hugsvision/dataio/ObjectDetectionCollator.py
hugsvision/dataio/VisionDataset.py
hugsvision/dataio/__init__.py
hugsvision/inference/ObjectDetectionInference.py
hugsvision/inference/TorchVisionClassifierInference.py
hugsvision/inference/VisionClassifierInference.py
hugsvision/inference/__init__.py
hugsvision/models/Detr.py
hugsvision/models/ViTForImageClassification.py
hugsvision/models/__init__.py
hugsvision/nnet/ObjectDetectionTrainer.py
hugsvision/nnet/TorchVisionClassifierTrainer.py
hugsvision/nnet/VisionClassifierTrainer.py
hugsvision/nnet/__init__.py
hugsvision/utils/ComputeImgMeanStd.py
hugsvision/utils/__init__.py
hugsvision-0.75.5.dist-info/LICENSE
hugsvision-0.75.5.dist-info/METADATA
hugsvision-0.75.5.dist-info/WHEEL
hugsvision-0.75.5.dist-info/top_level.txt
hugsvision-0.75.5.dist-info/RECORD
