Metadata-Version: 2.1
Name: hugsvision
Version: 0.75.5
Summary: A easy to use huggingface wrapper for computer vision.
Home-page: https://HugsVision.github.io/
Author: Yanis Labrak & Others
Author-email: yanis.labrak@univ-avignon.fr
License: UNKNOWN
Keywords: python,transformers,huggingface,wrapper,toolkit,computer vision,easy,computer,vision
Platform: UNKNOWN
Requires-Python: >=3.6
License-File: LICENSE
Requires-Dist: torch
Requires-Dist: torchvision
Requires-Dist: torchmetrics
Requires-Dist: Pillow
Requires-Dist: scikit-learn
Requires-Dist: transformers
Requires-Dist: tqdm
Requires-Dist: tabulate
Requires-Dist: timm
Requires-Dist: matplotlib
Requires-Dist: opencv-python
Requires-Dist: pytorch-lightning
Requires-Dist: pycocotools
